test/__init__.py
test/requirements.txt
test/symmetries.py
test/test_logging.py
test/test_retry.py
txrc/__init__.py
txrc/logging.py
txrc/retry.py
txrc/version.py
txrc-0.2.3.dist-info/DESCRIPTION.rst
txrc-0.2.3.dist-info/METADATA
txrc-0.2.3.dist-info/RECORD
txrc-0.2.3.dist-info/WHEEL
txrc-0.2.3.dist-info/metadata.json
txrc-0.2.3.dist-info/top_level.txt
