Metadata-Version: 2.0
Name: txrc
Version: 0.2.3
Summary: Twisted Retrying Caller Inspired by Terry Jones
Home-page: https://txrc.readthedocs.org/en/v0.2.3/
Author: Matt Bogosian
Author-email: matt@bogosian.net
License: MIT License
Platform: UNKNOWN
Classifier: Topic :: Software Development :: Libraries :: Python Modules
Classifier: Development Status :: 4 - Beta
Classifier: Framework :: Twisted
Classifier: Intended Audience :: Developers
Classifier: License :: OSI Approved :: MIT License
Classifier: Operating System :: OS Independent
Classifier: Programming Language :: Python
Classifier: Programming Language :: Python :: 2.7
Classifier: Programming Language :: Python :: 3.3
Classifier: Programming Language :: Python :: 3.4
Classifier: Programming Language :: Python :: 3.5
Classifier: Programming Language :: Python :: 3.6
Classifier: Programming Language :: Python :: Implementation :: CPython
Classifier: Programming Language :: Python :: Implementation :: PyPy
Requires-Dist: Twisted (>=15.2)
Requires-Dist: future
